Metadata-Version: 2.1
Name: bronotes
Version: 2.4.1
Summary: A commandline note organization tool.
Home-page: https://github.com/jwizzle/bronotes
Author: j wizzle
Author-email: info@hossel.net
License: UNKNOWN
Platform: UNKNOWN
Classifier: Programming Language :: Python :: 3
Classifier: License :: OSI Approved :: MIT License
Classifier: Operating System :: OS Independent
Requires-Python: >=3.7
Requires-Dist: pyyaml
Requires-Dist: shtab
Requires-Dist: pyperclip
Requires-Dist: gitpython
Requires-Dist: fuzzy-match
Requires-Dist: numpy
